dig_spider/__init__.py
dig_spider/cmdline.py
dig_spider/middlewares.py
dig_spider/pipelines.py
dig_spider/running.py
dig_spider/scrapy.cfg
dig_spider/settings.py
dig_spider/engine/__init__.py
dig_spider/engine/config.py
dig_spider/engine/extract.py
dig_spider/examples/__init__.py
dig_spider/examples/run_dig_spider.py
dig_spider/examples/config/css_example.yaml
dig_spider/examples/config/github.yaml
dig_spider/examples/config/json.py
dig_spider/examples/config/json_example.yaml
dig_spider/examples/config/re_example.yaml
dig_spider/examples/config/xpath_example.yaml
dig_spider/spiders/__init__.py
dig_spider/spiders/website.py
dig_spider/store/__init__.py
dig_spider/store/store.py
dig_spider/template/code_template.py
dig_spider/template/config_template.yaml
dig_spider/template/run_dig_spider.sh
dig_spider-0.1.0.dist-info/LICENSE
dig_spider-0.1.0.dist-info/METADATA
dig_spider-0.1.0.dist-info/WHEEL
dig_spider-0.1.0.dist-info/entry_points.txt
dig_spider-0.1.0.dist-info/top_level.txt
dig_spider-0.1.0.dist-info/RECORD
